{
  "id": "54055",
  "title": "Word Chef Search Puzzle",
  "slug": "word-chef-search-puzzle",
  "description": "Welcome to the Word Chef Search Puzzle, where you embark on a culinary adventure through a savory maze of letters to uncover delicious words hidden within! Web Dev <a href='https://www.funcrazygames.com/'>https://www.funcrazygames.com/</a>",
  "instructions": "Mouse click or tap to play",
  "url": "https://html5.gamemonetize.com/rsyanftvgq9tz4kb6wjxkhxc941ptz92/",
  "category": "Puzzle",
  "categorySlug": "puzzle",
  "tags": [
    "Boy",
    "Boys",
    "Educational",
    "Kids",
    "Mentolatux",
    "Puzzle",
    "Unity3D",
    "Word"
  ],
  "thumb": "https://img.gamemonetize.com/rsyanftvgq9tz4kb6wjxkhxc941ptz92/512x384.jpg",
  "width": 800,
  "height": 600,
  "publisher": "BestCrazyGames",
  "crawledAt": "2026-01-31T16:55:25.821Z"
}