{
  "id": "55680",
  "title": "Monsterr Match",
  "slug": "monsterr-match",
  "description": "Collect the maximum score by exploding the tiles.",
  "instructions": "You can explode the tiles by Mouse click or Tap on it only if there are three or more similar adjacent tiles Find the maximum score before the tile touches the top ",
  "url": "https://html5.gamemonetize.com/m9bozq3pg2vywfq8mlgupk8sf9ceosl7/",
  "category": "Puzzle",
  "categorySlug": "puzzle",
  "tags": [
    "Block",
    "Brain",
    "Casual",
    "Clicker",
    "Color",
    "Kids",
    "Logic",
    "Match 3",
    "Match3",
    "Matching",
    "Monster",
    "Puzzle",
    "puzzleblock"
  ],
  "thumb": "https://img.gamemonetize.com/m9bozq3pg2vywfq8mlgupk8sf9ceosl7/512x384.jpg",
  "width": 540,
  "height": 960,
  "publisher": null,
  "crawledAt": "2026-02-01T04:24:31.688Z"
}