{
  "id": "54519",
  "title": "Connect Joy",
  "slug": "connect-joy",
  "description": "Welcome to Connect Joy, the exciting Onet puzzle game! Sharpen your mind by connecting 2 identical elements on the board. Tap or click to link two identical tiles with exactly three straight turns to link matching pairs. Explore a vast world of challenging levels and race against the clock to clear the board before time runs out. Good luck!",
  "instructions": " Tap or click to play ",
  "url": "https://html5.gamemonetize.com/e1ku2c5lpyco6skxz2k6ltvqyjjlk9lz/",
  "category": "Puzzle",
  "categorySlug": "puzzle",
  "tags": [
    "Mahjong",
    "Matching",
    "Puzzle"
  ],
  "thumb": "https://img.gamemonetize.com/e1ku2c5lpyco6skxz2k6ltvqyjjlk9lz/512x384.jpg",
  "width": 720,
  "height": 1280,
  "publisher": "SoulHouse",
  "crawledAt": "2026-02-01T07:33:23.332Z"
}